hid-stubs/__init__.pyi
hidapi_stubs-0.14.0.post1.dist-info/METADATA
hidapi_stubs-0.14.0.post1.dist-info/WHEEL
hidapi_stubs-0.14.0.post1.dist-info/top_level.txt
hidapi_stubs-0.14.0.post1.dist-info/RECORD
