Metadata-Version: 2.1
Name: hidapi-stubs
Version: 0.14.0.post1
Summary: Stubs for cython-hidapi
Author-email: HivertMoZara <worldmozara@163.com>
License: MIT
Project-URL: Homepage, https://github.com/NCBM/cython-hidapi-stubs
Project-URL: Repository, https://github.com/NCBM/cython-hidapi-stubs
Requires-Python: >=3.5
Requires-Dist: hidapi <0.15,>=0.14.0
